amberflow/__init__.py
amberflow/campaign.py
amberflow/checkpoint.py
amberflow/distributed.py
amberflow/pipeline.py
amberflow/artifacts/__init__.py
amberflow/artifacts/alchemical.py
amberflow/artifacts/artifactsdecorators.py
amberflow/artifacts/baseartifact.py
amberflow/artifacts/fileutils.py
amberflow/artifacts/md.py
amberflow/artifacts/md.pyi
amberflow/artifacts/misc.py
amberflow/artifacts/structure.py
amberflow/artifacts/topology.py
amberflow/artifacts/trajectory.py
amberflow/cli/__init__.py
amberflow/cli/cptool.py
amberflow/cli/printdag.py
amberflow/cli/printflow.py
amberflow/cli/printworknode.py
amberflow/cli/runflow.py
amberflow/customartifacts/__init__.py
amberflow/customartifacts/timsdock.py
amberflow/customflows/__init__.py
amberflow/customflows/boxrelax1.py
amberflow/customflows/timsdocking1.py
amberflow/customflows/timsdocking2.py
amberflow/customworknodes/__init__.py
amberflow/customworknodes/boxligand.py
amberflow/customworknodes/processtim.py
amberflow/customworknodes/timsbuildtemplate.py
amberflow/customworknodes/timsmask.py
amberflow/data/cpptraj/autoimage
amberflow/data/cpptraj/go
amberflow/data/cpptraj/parm
amberflow/data/cpptraj/rms_first
amberflow/data/cpptraj/rms_reference_out
amberflow/data/cpptraj/strip
amberflow/data/cpptraj/trajin
amberflow/data/cpptraj/trajout
amberflow/data/mdin/as
amberflow/data/mdin/mbar_lambda
amberflow/data/mdin/md
amberflow/data/mdin/md_icfe
amberflow/data/mdin/md_icfe_nmropt
amberflow/data/mdin/md_icfe_nmropt_varying
amberflow/data/mdin/md_icfe_noneq
amberflow/data/mdin/md_icfe_noneq_nmropt
amberflow/data/mdin/md_icfe_noneq_nmropt_varying
amberflow/data/mdin/md_icfe_noneq_restrained
amberflow/data/mdin/md_icfe_noneq_restrained_nmropt
amberflow/data/mdin/md_icfe_noneq_restrained_nmropt_varying
amberflow/data/mdin/md_icfe_noneq_restrained_rmsd
amberflow/data/mdin/md_icfe_noneq_restrained_rmsd2
amberflow/data/mdin/md_icfe_noneq_restrained_rmsd2_nmropt
amberflow/data/mdin/md_icfe_noneq_restrained_rmsd2_nmropt_varying
amberflow-0.3.7.dist-info/METADATA
amberflow-0.3.7.dist-info/WHEEL
amberflow-0.3.7.dist-info/entry_points.txt
amberflow-0.3.7.dist-info/licenses/LICENSE.txt
amberflow-0.3.7.dist-info/RECORD
