Metadata-Version: 2.4
Name: amberflow
Version: 0.3.7
Summary: Python workflow to run Free Energy calculations
Project-URL: Documentation, https://github.com/pgbarletta/amberflow#readme
Project-URL: Issues, https://github.com/pgbarletta/amberflow/issues
Project-URL: Source, https://github.com/pgbarletta/amberflow
Author-email: pgbarletta <pbarletta@gmail.com>
License-Expression: MIT
License-File: LICENSE.txt
Classifier: Development Status :: 4 - Beta
Classifier: Programming Language :: Python
Classifier: Programming Language :: Python :: 3.8
Classifier: Programming Language :: Python :: 3.9
Classifier: Programming Language :: Python :: 3.10
Classifier: Programming Language :: Python :: 3.11
Classifier: Programming Language :: Python :: 3.12
Classifier: Programming Language :: Python :: Implementation :: CPython
Classifier: Programming Language :: Python :: Implementation :: PyPy
Requires-Python: >=3.10
Requires-Dist: attrs
Requires-Dist: biopython
Requires-Dist: edgembar
Requires-Dist: hatch>=1.14.1
Requires-Dist: ligandparam
Requires-Dist: mdanalysis
Requires-Dist: networkx
Requires-Dist: numpy<2
Requires-Dist: parmed
Requires-Dist: pydot
Requires-Dist: pyyaml
Requires-Dist: scipy
Requires-Dist: typing-extensions
Requires-Dist: zstandard>=0.23.0
Provides-Extra: all
Requires-Dist: boto3; extra == 'all'
Requires-Dist: furo>=2025.7.19; extra == 'all'
Requires-Dist: myst-parser>=4.0.1; extra == 'all'
Requires-Dist: ruff>=0.12.8; extra == 'all'
Requires-Dist: scipy-stubs; extra == 'all'
Requires-Dist: sphinx-autobuild>=2024; extra == 'all'
Requires-Dist: sphinx-copybutton>=0.5; extra == 'all'
Requires-Dist: sphinx-inline-tabs>=2023; extra == 'all'
Requires-Dist: sphinx-rtd-theme>=3; extra == 'all'
Requires-Dist: sphinx>=8.2; extra == 'all'
Provides-Extra: aws
Requires-Dist: boto3; extra == 'aws'
Provides-Extra: dev
Requires-Dist: ruff>=0.12.8; extra == 'dev'
Requires-Dist: scipy-stubs; extra == 'dev'
Provides-Extra: docs
Requires-Dist: furo>=2025.7.19; extra == 'docs'
Requires-Dist: myst-parser>=4.0.1; extra == 'docs'
Requires-Dist: sphinx-autobuild>=2024; extra == 'docs'
Requires-Dist: sphinx-copybutton>=0.5; extra == 'docs'
Requires-Dist: sphinx-inline-tabs>=2023; extra == 'docs'
Requires-Dist: sphinx-rtd-theme>=3; extra == 'docs'
Requires-Dist: sphinx>=8.2; extra == 'docs'
